asciikid.py
asciikid-0.2.1.dist-info/licenses/LICENSE
asciikid-0.2.1.dist-info/METADATA
asciikid-0.2.1.dist-info/WHEEL
asciikid-0.2.1.dist-info/entry_points.txt
asciikid-0.2.1.dist-info/top_level.txt
asciikid-0.2.1.dist-info/RECORD
