Metadata-Version: 2.4
Name: asciikid
Version: 0.2.1
Summary: A fun and simple TUI for kids to draw and write text creatively
Author-email: Philippe Proulx <eeppeliteloop@gmail.com>
License-Expression: MIT
Project-URL: Homepage, https://github.com/eepp/asciikid
Requires-Python: >=3.11
License-File: LICENSE
Requires-Dist: blessed~=1.23
Dynamic: license-file
